mux.v
// output is A (when control == 0) or B (when control == 1)
module mux2(out, A, B, control);
    output out;
    input  A, B;
    input  control;
    wire   wA, wB, not_control;

    not n1(not_control, control);
    and a1(wA, A, not_control);
    and a2(wB, B, control);
    or  o1(out, wA, wB);
endmodule // mux2

// output is A (when control == 00) or B (when control == 01) or
//           C (when control == 10) or D (when control == 11)
module mux4(out, A, B, C, D, control);
    output      out;
    input       A, B, C, D;
    input [1:0] control;
    wire w1, w2;
    mux2 m1(w1, A, B, control[0]);
    mux2 m2(w2, C, D, control[0]);
    mux2 m3(out, w1, w2, control[1]);

endmodule // mux4

logicunit.v
// 00 -> AND, 01 -> OR, 10 -> NOR, 11 -> XOR
module logicunit(out, A, B, control);
    output      out;
    input       A, B;
    input [1:0] control;

    wire w1, w2, w3, w4;
    and a1(w1, A, B);
    or o1(w2, A, B);
    nor n1(w3, A, B);
    xor x1(w4, A, B);
    mux4 m2(out, w1, w2, w3, w4, control);




endmodule // logicunit

alu1.v
module full_adder(sum, cout, a, b, cin);
    output sum, cout;
    input  a, b, cin;
    wire   partial_s, partial_c1, partial_c2;

    xor x0(partial_s, a, b);
    xor x1(sum, partial_s, cin);
    and a0(partial_c1, a, b);
    and a1(partial_c2, partial_s, cin);
    or  o1(cout, partial_c1, partial_c2);
endmodule // full_adder

`define ALU_ADD    3'h2
`define ALU_SUB    3'h3
`define ALU_AND    3'h4
`define ALU_OR     3'h5
`define ALU_NOR    3'h6
`define ALU_XOR    3'h7

// 01x -> arithmetic, 1xx -> logic
module alu1(out, carryout, A, B, carryin, control);
    output      out, carryout;
    input       A, B, carryin;
    input [2:0] control;
    wire xor_input, sum, logicout;

    xor x1(xor_input, B, control[0]);
    full_adder f1(sum, carryout, A, xor_input, carryin);
    logicunit l1(logicout, A, B, control[1:0]);
    mux2 m2(out, logicout, sum, control[2]);


endmodule // alu1

alu1_tb.v
module alu1_test;
    // exhaustively test your 1-bit ALU implementation by adapting mux4_tb.v

    // cycle through all combinations of A, B, C, D every 16 time units
    reg A = 0;
    always #1 A = !A;
    reg B = 0;
    always #2 B = !B;
    reg carryin = 0;
    always #3 carryin = !carryin;


    reg [2:0] control = 0;

    initial begin
        $dumpfile("alu1.vcd");
        $dumpvars(0, alu1_test);

        // control is initially 0
        # 16 control = 1; // wait 16 time units (why 16?) and then set it to 1
        # 16 control = 2; // wait 16 time units and then set it to 2
        # 16 control = 3; // wait 16 time units and then set it to 3
        # 16 $finish; // wait 16 time units and then end the simulation
    end

    wire out, carryout;
    alu1 a1(out, carryout, carryin, A, B, control);

    // you really should be using gtkwave instead

    /*initial begin
        $display("A B carryin out control carryout");
        $monitor("%d %d %d %d %d %d(at time %t)", A, B, carryin, out, control, carryout $time);
    end
    */

endmodule

alu1.vcd
$date
	Fri Sep 13 12:24:06 2019
$end
$version
	Icarus Verilog
$end
$timescale
	1s
$end
$scope module alu1_test $end
$var wire 1 ! out $end
$var wire 1 " carryout $end
$var reg 1 # A $end
$var reg 1 $ B $end
$var reg 1 % carryin $end
$var reg 3 & control [2:0] $end
$scope module a1 $end
$var wire 1 % A $end
$var wire 1 # B $end
$var wire 1 $ carryin $end
$var wire 3 ' control [2:0] $end
$var wire 1 ( xor_input $end
$var wire 1 ) sum $end
$var wire 1 ! out $end
$var wire 1 * logicout $end
$var wire 1 " carryout $end
$scope module f1 $end
$var wire 1 % a $end
$var wire 1 ( b $end
$var wire 1 $ cin $end
$var wire 1 " cout $end
$var wire 1 + partial_c1 $end
$var wire 1 , partial_c2 $end
$var wire 1 - partial_s $end
$var wire 1 ) sum $end
$upscope $end
$scope module l1 $end
$var wire 1 % A $end
$var wire 1 # B $end
$var wire 2 . control [1:0] $end
$var wire 1 / w1 $end
$var wire 1 0 w2 $end
$var wire 1 1 w3 $end
$var wire 1 2 w4 $end
$var wire 1 * out $end
$scope module m2 $end
$var wire 1 / A $end
$var wire 1 0 B $end
$var wire 1 1 C $end
$var wire 1 2 D $end
$var wire 2 3 control [1:0] $end
$var wire 1 4 w2 $end
$var wire 1 5 w1 $end
$var wire 1 * out $end
$scope module m1 $end
$var wire 1 / A $end
$var wire 1 0 B $end
$var wire 1 6 control $end
$var wire 1 7 not_control $end
$var wire 1 5 out $end
$var wire 1 8 wA $end
$var wire 1 9 wB $end
$upscope $end
$scope module m2 $end
$var wire 1 1 A $end
$var wire 1 2 B $end
$var wire 1 : control $end
$var wire 1 ; not_control $end
$var wire 1 4 out $end
$var wire 1 < wA $end
$var wire 1 = wB $end
$upscope $end
$scope module m3 $end
$var wire 1 5 A $end
$var wire 1 4 B $end
$var wire 1 > control $end
$var wire 1 ? not_control $end
$var wire 1 * out $end
$var wire 1 @ wA $end
$var wire 1 A wB $end
$upscope $end
$upscope $end
$upscope $end
$scope module m2 $end
$var wire 1 * A $end
$var wire 1 ) B $end
$var wire 1 B control $end
$var wire 1 C not_control $end
$var wire 1 ! out $end
$var wire 1 D wA $end
$var wire 1 E wB $end
$upscope $end
$upscope $end
$upscope $end
$enddefinitions $end
#0
$dumpvars
0E
0D
1C
0B
0A
0@
1?
0>
0=
1<
1;
0:
09
08
17
06
05
14
b0 3
02
11
00
0/
b0 .
0-
0,
0+
0*
0)
0(
b0 '
b0 &
0%
0$
0#
0"
0!
$end
#1
1)
04
1-
0<
1(
10
01
12
1#
#2
14
0-
1<
0"
0(
00
11
02
1)
0,
0#
1$
#3
1!
1D
1*
1@
1"
15
04
1+
1)
0,
18
0<
1(
0-
1/
10
01
1#
1%
#4
0!
0D
0*
0@
0"
05
1-
0+
08
0(
0/
12
1)
0#
0$
#5
1!
1D
1*
1@
0)
1"
15
0-
1+
18
1(
1/
02
1#
#6
0!
0D
0*
0"
0@
1)
05
14
08
1<
0(
0,
0-
0+
0/
00
11
0#
1$
0%
#7
1"
0)
1,
04
1-
0<
1(
10
01
12
1#
#8
14
0-
1<
0"
0(
00
11
02
0)
0,
0#
0$
#9
1!
1D
1*
1@
1"
15
04
1+
0)
18
0<
1(
0-
1/
10
01
1#
1%
#10
0!
0D
0*
0@
1,
1"
05
1-
0+
08
0(
0/
12
0)
0#
1$
#11
1!
1D
1*
1@
1)
0,
15
0-
1+
18
1(
1/
02
1#
#12
0!
0D
0*
0@
0)
05
14
0"
08
1<
0(
0-
0+
0/
00
11
0#
0$
0%
#13
1)
04
1-
0<
1(
10
01
12
1#
#14
14
0-
1<
0"
0(
00
11
02
1)
0,
0#
1$
#15
1!
1D
1*
1@
1"
15
04
1+
1)
0,
18
0<
1(
0-
1/
10
01
1#
1%
#16
14
07
19
0;
08
1=
16
1:
0/
12
0)
b1 .
b1 3
0#
0$
b1 &
b1 '
#17
1)
0"
04
1-
0+
0=
0(
1/
02
1#
#18
0!
0D
0*
1"
0@
0)
1,
05
09
1(
1-
0/
00
11
0#
1$
0%
#19
1!
1D
1*
0"
1@
1)
0,
15
14
0-
19
1=
0(
10
01
12
1#
#20
0!
0D
0*
0@
05
04
1-
09
0=
1(
00
11
02
1)
0#
0$
#21
1!
1D
1*
1@
15
1)
0"
19
0(
1-
0+
1/
10
01
1#
1%
#22
14
0-
1+
1=
1"
1(
0/
12
1)
0,
0#
1$
#23
0)
1,
1"
04
1-
0+
0=
0(
1/
02
1#
#24
0!
0D
0*
0@
1)
05
0"
09
1(
0,
1-
0/
00
11
0#
0$
0%
#25
1!
1D
1*
1@
0)
15
14
0-
19
1=
0(
10
01
12
1#
#26
0!
0D
0*
1"
0@
1,
05
04
1-
09
0=
1(
00
11
02
0)
0#
1$
#27
1!
1D
1*
1@
1"
15
0)
1,
19
0(
1-
0+
1/
10
01
1#
1%
#28
14
0-
1+
1=
1"
1(
0/
12
0)
0,
0#
0$
#29
1)
0"
04
1-
0+
0=
0(
1/
02
1#
#30
0!
0D
0*
1"
0@
0)
1,
05
09
1(
1-
0/
00
11
0#
1$
0%
#31
1!
1D
1*
0"
1@
1)
0,
15
14
0-
19
1=
0(
10
01
12
1#
#32
1!
1D
1*
1<
0@
05
14
17
1;
0?
1A
09
0=
06
0:
1>
00
11
02
0)
b10 .
b10 3
0#
0$
b10 &
b10 '
#33
0!
0D
0*
0A
1"
15
04
1+
0)
18
0<
1(
0-
1/
10
01
1#
1%
#34
1,
1"
05
1-
0+
08
0(
0/
12
0)
0#
1$
#35
1)
0,
15
0-
1+
18
1(
1/
02
1#
#36
1!
1D
1*
1A
0)
05
14
0"
08
1<
0(
0-
0+
0/
00
11
0#
0$
0%
#37
0!
0D
0*
0A
1)
04
1-
0<
1(
10
01
12
1#
#38
1!
1D
1*
1A
14
0-
1<
0"
0(
00
11
02
1)
0,
0#
1$
#39
0!
0D
0*
0A
1"
15
04
1+
1)
0,
18
0<
1(
0-
1/
10
01
1#
1%
#40
0"
05
1-
0+
08
0(
0/
12
1)
0#
0$
#41
0)
1"
15
0-
1+
18
1(
1/
02
1#
#42
1!
1D
1*
0"
1A
1)
05
14
08
1<
0(
0,
0-
0+
0/
00
11
0#
1$
0%
#43
0!
0D
0*
1"
0A
0)
1,
04
1-
0<
1(
10
01
12
1#
#44
1!
1D
1*
1A
14
0-
1<
0"
0(
00
11
02
0)
0,
0#
0$
#45
0!
0D
0*
0A
1"
15
04
1+
0)
18
0<
1(
0-
1/
10
01
1#
1%
#46
1,
1"
05
1-
0+
08
0(
0/
12
0)
0#
1$
#47
1)
0,
15
0-
1+
18
1(
1/
02
1#
#48
0!
0D
0*
0A
05
04
07
0;
0"
08
0<
16
1:
1-
0+
0/
00
11
b11 .
b11 3
0#
0$
0%
b11 &
b11 '
#49
1!
1D
1*
1A
0)
15
14
0-
19
1=
0(
10
01
12
1#
#50
0!
0D
0*
1"
0A
1,
05
04
1-
09
0=
1(
00
11
02
0)
0#
1$
#51
1"
15
0)
1,
19
0(
1-
0+
1/
10
01
1#
1%
#52
1!
1D
1*
1A
14
0-
1+
1=
1"
1(
0/
12
0)
0,
0#
0$
#53
0!
0D
0*
0A
1)
0"
04
1-
0+
0=
0(
1/
02
1#
#54
1"
0)
1,
05
09
1(
1-
0/
00
11
0#
1$
0%
#55
1!
1D
1*
0"
1A
1)
0,
15
14
0-
19
1=
0(
10
01
12
1#
#56
0!
0D
0*
0A
05
04
1-
09
0=
1(
00
11
02
1)
0#
0$
#57
15
1)
0"
19
0(
1-
0+
1/
10
01
1#
1%
#58
1!
1D
1*
1A
14
0-
1+
1=
1"
1(
0/
12
1)
0,
0#
1$
#59
0!
0D
0*
0A
0)
1,
1"
04
1-
0+
0=
0(
1/
02
1#
#60
1)
05
0"
09
1(
0,
1-
0/
00
11
0#
0$
0%
#61
1!
1D
1*
1A
0)
15
14
0-
19
1=
0(
10
01
12
1#
#62
0!
0D
0*
1"
0A
1,
05
04
1-
09
0=
1(
00
11
02
0)
0#
1$
#63
1"
15
0)
1,
19
0(
1-
0+
1/
10
01
1#
1%
#64
1!
1D
1*
1A
14
0-
1+
1=
1"
1(
0/
12
0)
0,
0#
0$
